malin/__init__.py
malin/actions/__init__.py
malin/actions/scan.py
malin/actions/update.py
malin/errors/__init__.py
malin/errors/engine_error.py
malin/errors/parser_error.py
malin/malin.py
malin/models/__init__.py
malin/models/response.py
malin/models/scan_error.py
malin-0.2.2.dist-info/LICENSE.md
malin-0.2.2.dist-info/METADATA
malin-0.2.2.dist-info/WHEEL
malin-0.2.2.dist-info/RECORD
