Metadata-Version: 2.1
Name: malin
Version: 0.2.2
Summary: 
Author: Yassine Damiri
Author-email: yassine.damiri@epita.fr
Requires-Python: >=3.12,<4.0
Classifier: Programming Language :: Python :: 3
Classifier: Programming Language :: Python :: 3.12
Requires-Dist: flask (>=3.0.3,<4.0.0)
